<?xml version="1.0" encoding="utf-8" ?>
<dwsync>
<file name="InverseKinematics8.swf" server="ftp.laughinglance.com/public_html/" local="131250912960714606" remote="131254596000000000" Dst="1" />
<file name="InverseKinematics8.html" server="ftp.laughinglance.com/public_html/" local="131254600507069280" remote="131254600200000000" Dst="1" />
<file name="squishy robot ball.swf" server="ftp.laughinglance.com/public_html/" local="131250849575574697" remote="131254596000000000" Dst="1" />
<file name="squishy robot ball.html" server="ftp.laughinglance.com/public_html/" local="131254600210000000" remote="131254600200000000" Dst="1" />
<file name="InverseKinematics8.html" server="35.161.85.48//var/www/html/" local="131359714000745913" remote="131359714290000000" Dst="2" />
<file name="InverseKinematics8.swf" server="35.161.85.48//var/www/html/" local="131250912960714606" remote="131359238910000000" Dst="2" />
<file name="squishy robot ball.html" server="35.161.85.48//var/www/html/" local="131359714185548218" remote="131359714290000000" Dst="2" />
<file name="squishy robot ball.swf" server="35.161.85.48//var/www/html/" local="131250849575574697" remote="131359238910000000" Dst="2" />
</dwsync>